<?xml version="1.0" encoding="UTF-8"?>

<!--
  ~ Copyright (c) 2015 Cisco Systems, Inc. and others.  All rights reserved.
  ~
  ~ This program and the accompanying materials are made available under the
  ~ terms of the Eclipse Public License v1.0 which accompanies this distribution,
  ~ and is available at http://www.eclipse.org/legal/epl-v10.html
  -->

<features name="openflowplugin-applications-frs-${project.version}" xmlns="http://karaf.apache.org/xmlns/features/v1.2.0"
          xmlns:xsi="http://www.w3.org/2001/XMLSchema-instance"
          xsi:schemaLocation="http://karaf.apache.org/xmlns/features/v1.2.0 http://karaf.apache.org/xmlns/features/v1.2.0">
    <repository>mvn:org.opendaylight.controller/features-mdsal/${mdsal.version}/xml/features</repository>
    <repository>mvn:org.opendaylight.netconf/features-netconf-connector/${netconf.version}/xml/features</repository>
    <repository>mvn:org.opendaylight.yangtools/features-yangtools/${yangtools.version}/xml/features</repository>

    <!-- DEV COMMAND SUPPORT -->
    <feature name='odl-openflowplugin-application-frsync' description="OpenDaylight :: Openflow Plugin :: FR-Synchronization" version='${project.version}'>
        <feature version='${netconf.version}'>odl-netconf-connector-all</feature>
        <feature version='${mdsal.version}'>odl-netconf-mdsal</feature>
        <bundle>mvn:org.opendaylight.openflowplugin.applications/forwardingrules-manager/${project.version}</bundle>
        <bundle>mvn:org.opendaylight.openflowplugin.applications/forwardingrules-sync/${project.version}</bundle>
        <configfile finalname="etc/opendaylight/karaf/69-forwardingrules-sync.xml">mvn:org.opendaylight.openflowplugin.applications/forwardingrules-sync/${project.version}/xml/config</configfile>
    </feature>

</features>
